fundamentalanalysis/__init__.py
fundamentalanalysis-0.3.1.dist-info/LICENSE
fundamentalanalysis-0.3.1.dist-info/METADATA
fundamentalanalysis-0.3.1.dist-info/WHEEL
fundamentalanalysis-0.3.1.dist-info/RECORD
