Metadata-Version: 2.1
Name: fundamentalanalysis
Version: 0.3.1
Summary: Fully-fledged Fundamental Analysis package capable of collecting 20 years of Company Profiles, Financial Statements, Ratios and Stock Data of 20.000+ companies
Home-page: https://www.jeroenbouma.com/
License: MIT
Author: Jeroen Bouma
Requires-Python: >=3.10,<3.13
Classifier: Development Status :: 5 - Production/Stable
Classifier: Intended Audience :: Financial and Insurance Industry
Classifier: License :: OSI Approved :: MIT License
Classifier: Operating System :: OS Independent
Classifier: Programming Language :: Python :: 3
Classifier: Programming Language :: Python :: 3.10
Classifier: Programming Language :: Python :: 3.11
Classifier: Programming Language :: Python :: 3.12
Classifier: Topic :: Office/Business :: Financial :: Investment
Requires-Dist: financedatabase (>=2.2.0,<3.0.0)
Requires-Dist: financetoolkit (>=1.3.5,<2.0.0)
Requires-Dist: pandas[computation,performance,plot] (>=2.1.0,<3.0.0)
Project-URL: Repository, https://github.com/JerBouma/FinanceToolkit
